uwl_client/__init__.py
uwl_client/calculate_signature.py
uwl_client/client.py
uwl_client/uwl_client.py
uwl_v2_client-0.1.1.dist-info/licenses/LICENSE
uwl_v2_client-0.1.1.dist-info/METADATA
uwl_v2_client-0.1.1.dist-info/WHEEL
uwl_v2_client-0.1.1.dist-info/top_level.txt
uwl_v2_client-0.1.1.dist-info/RECORD
