Metadata-Version: 2.4
Name: uwl-v2-client
Version: 0.1.1
Summary: An unofficial Python client for the WeatherLink v2 API
Author-email: Ricardo Daniel Quiroga <l2radamanthys@gmail.com>
License-Expression: MIT
Project-URL: Homepage, https://github.com/l2radamanthys/uwl-v2-client
Project-URL: Issues, https://github.com/l2radamanthys/uwl-v2-client/issues
Classifier: Programming Language :: Python :: 3
Classifier: Operating System :: OS Independent
Requires-Python: >=3.8
License-File: LICENSE
Requires-Dist: requests
Requires-Dist: python-dateutil
Dynamic: license-file
